src/__init__.py
src/__main__.py
tnalgo/__init__.py
tnalgo/__main__.py
tnalgo-1.0.4.dist-info/LICENSE
tnalgo-1.0.4.dist-info/METADATA
tnalgo-1.0.4.dist-info/WHEEL
tnalgo-1.0.4.dist-info/entry_points.txt
tnalgo-1.0.4.dist-info/top_level.txt
tnalgo-1.0.4.dist-info/RECORD
