Metadata-Version: 2.1
Name: tnalgo
Version: 1.0.4
Summary: A set of algorithmic functions
Home-page: https://github.com/manimanis/tnalgo
Author: Mohamed Anis MANI
Author-email: manimohamed@gmail.com
License: MIT
Platform: UNKNOWN
Classifier: License :: OSI Approved :: MIT License
Classifier: Programming Language :: Python :: 3.6
Classifier: Programming Language :: Python :: 3.7
Classifier: Programming Language :: Python :: 3.8
Classifier: Programming Language :: Python :: 3.9
